quickvision/__init__.py
quickvision/datasets/__init__.py
quickvision/datasets/classification.py
quickvision/datasets/detection.py
quickvision/layers/__init__.py
quickvision/layers/act_mish.py
quickvision/layers/block_mlp.py
quickvision/layers/functional/__init__.py
quickvision/layers/functional/act_mish.py
quickvision/losses/__init__.py
quickvision/losses/detr_loss.py
quickvision/losses/dice_loss.py
quickvision/losses/functional/__init__.py
quickvision/losses/functional/dice_loss.py
quickvision/metrics/__init__.py
quickvision/metrics/classification.py
quickvision/models/__init__.py
quickvision/models/classification/__init__.py
quickvision/models/classification/cnn/__init__.py
quickvision/models/classification/cnn/engine.py
quickvision/models/classification/cnn/lightning_trainer.py
quickvision/models/classification/cnn/model_factory.py
quickvision/models/classification/cnn/utils.py
quickvision/models/components/__init__.py
quickvision/models/components/torchvision_backbones.py
quickvision/models/detection/__init__.py
quickvision/models/detection/utils.py
quickvision/models/detection/detr/__init__.py
quickvision/models/detection/detr/engine.py
quickvision/models/detection/detr/lightning_trainer.py
quickvision/models/detection/detr/model_factory.py
quickvision/models/detection/detr/utils.py
quickvision/models/detection/faster_rcnn/__init__.py
quickvision/models/detection/faster_rcnn/engine.py
quickvision/models/detection/faster_rcnn/lightning_trainer.py
quickvision/models/detection/faster_rcnn/model_factory.py
quickvision/models/detection/retinanet/__init__.py
quickvision/models/detection/retinanet/engine.py
quickvision/models/detection/retinanet/lightning_trainer.py
quickvision/models/detection/retinanet/model_factory.py
quickvision/models/segmentation/__init__.py
quickvision/models/segmentation/deeplab/__init__.py
quickvision/models/segmentation/fcn/__init__.py
quickvision/optimizers/__init__.py
quickvision/pretrained/__init__.py
quickvision/pretrained/_model_zoo.py
quickvision-0.2.1.dist-info/LICENSE
quickvision-0.2.1.dist-info/METADATA
quickvision-0.2.1.dist-info/WHEEL
quickvision-0.2.1.dist-info/top_level.txt
quickvision-0.2.1.dist-info/RECORD
