Metadata-Version: 2.1
Name: quickvision
Version: 0.2.1
Summary: Computer Vision models and training
Home-page: UNKNOWN
Author: Aditya Oke
Author-email: okeaditya315@gmail.com
License: apache2
Download-URL: https://github.com/Quick-AI/quickvision
Project-URL: Bug Tracker, https://github.com/Quick-AI/quickvision/issues
Project-URL: Documentation, https://quick-ai.github.io/quickvision/
Project-URL: Source Code, https://github.com/Quick-AI/quickvision
Keywords: Deep Learning,PyTorch
Platform: UNKNOWN
Classifier: Environment :: Console
Classifier: Natural Language :: English
Classifier: Development Status :: 3 - Alpha
Classifier: Intended Audience :: Developers
Classifier: Topic :: Scientific/Engineering :: Artificial Intelligence
Classifier: Topic :: Scientific/Engineering :: Image Recognition
Classifier: Topic :: Scientific/Engineering :: Information Analysis
Classifier: License :: OSI Approved :: Apache Software License
Classifier: Operating System :: OS Independent
Classifier: Programming Language :: Python :: 3
Classifier: Programming Language :: Python :: 3.6
Classifier: Programming Language :: Python :: 3.7
Classifier: Programming Language :: Python :: 3.8
Requires-Python: >=3.6
Requires-Dist: torch (==1.8.1)
Requires-Dist: torchvision (==0.9.1)
Requires-Dist: pytorch-lightning (==1.2.6)
Requires-Dist: scipy (==1.5.4)
